customtkinterbuilder/CodeGenerator.py
customtkinterbuilder/Logo-WelcomePage.png
customtkinterbuilder/Logo.ico
customtkinterbuilder/Logo.png
customtkinterbuilder/PackArgs.py
customtkinterbuilder/WelcomePage.py
customtkinterbuilder/__init__.py
customtkinterbuilder/__main__.py
customtkinterbuilder/config.json
customtkinterbuilder/ctk_widget.py.j2
customtkinterbuilder/ctk_widget_pack.py.j2
customtkinterbuilder/ctk_widget_pack_propagate.py.j2
customtkinterbuilder/dragndrop.py
customtkinterbuilder/get_path.py
customtkinterbuilder/hook-tkinterdnd2.py
customtkinterbuilder/main.py
customtkinterbuilder/properties.py
customtkinterbuilder/widgets.py
customtkinterbuilder/Assets/baseline_arrow_forward_white_18dp_1x.png
customtkinterbuilder/Assets/baseline_home_white_18dp_1x.png
customtkinterbuilder/Assets/baseline_logo_dev_white_48dp_2x.png
customtkinterbuilder/Assets/baseline_people_black_18dp_1x.png
customtkinterbuilder/Assets/baseline_people_white_18dp_1x.png
customtkinterbuilder/Assets/baseline_search_white_24dp_1x.png
customtkinterbuilder/Examples/HelloWorld/HelloWorld.json
customtkinterbuilder/Examples/Login-Demo/Login-Demo.json
customtkinterbuilder/Examples/Login-Demo/LoginDemo.py
"customtkinterbuilder/Examples/Login-Demo/Assets/baseline_logo_dev_(145, 91, 255)_24dp_2x.png"
customtkinterbuilder/Examples/Spotify-Demo/Spotify-Demo.json
customtkinterbuilder/Examples/Spotify-Demo/Spotify-Demo.py
"customtkinterbuilder/Examples/Spotify-Demo/Assets/baseline_add_(255, 255, 255)_18dp_1x.png"
"customtkinterbuilder/Examples/Spotify-Demo/Assets/baseline_favorite_(255, 255, 255)_18dp_1x.png"
"customtkinterbuilder/Examples/Spotify-Demo/Assets/baseline_favorite_border_(255, 255, 255)_18dp_1x.png"
"customtkinterbuilder/Examples/Spotify-Demo/Assets/baseline_home_(255, 255, 255)_18dp_1x.png"
"customtkinterbuilder/Examples/Spotify-Demo/Assets/baseline_library_music_(255, 255, 255)_18dp_1x.png"
customtkinterbuilder-1.0.3.dist-info/LICENSE
customtkinterbuilder-1.0.3.dist-info/METADATA
customtkinterbuilder-1.0.3.dist-info/WHEEL
customtkinterbuilder-1.0.3.dist-info/entry_points.txt
customtkinterbuilder-1.0.3.dist-info/top_level.txt
customtkinterbuilder-1.0.3.dist-info/RECORD
