Metadata-Version: 2.2
Name: customtkinterbuilder
Version: 1.0.3
Summary: This is a Free and Open Source RAD tool for Custom Tkinter. This software allows you to create complex UI faster than ever⚡
Home-page: https://github.com/rigvedmaanas/CustomTkinterBuilder
Author: Rigved Maanas M
Author-email: rigvedmaanas@gmail.com
Project-URL: Bug Tracker, https://github.com/rigvedmaanas/CustomTkinterBuilder/issues
Classifier: Programming Language :: Python :: 3
Classifier: License :: OSI Approved :: MIT License
Classifier: Operating System :: OS Independent
Requires-Python: >=3.9
License-File: LICENSE
Requires-Dist: asttokens==3.0.0
Requires-Dist: autopep8==2.3.2
Requires-Dist: backports.tarfile==1.2.0
Requires-Dist: certifi==2025.4.26
Requires-Dist: charset-normalizer==3.4.2
Requires-Dist: colorama==0.4.6
Requires-Dist: customtkinter==5.2.2
Requires-Dist: CustomtkinterCodeViewer==0.0.3
Requires-Dist: darkdetect==0.8.0
Requires-Dist: docutils==0.21.2
Requires-Dist: executing==2.2.0
Requires-Dist: icecream==2.1.4
Requires-Dist: id==1.5.0
Requires-Dist: idna==3.10
Requires-Dist: importlib_metadata==8.7.0
Requires-Dist: jaraco.classes==3.4.0
Requires-Dist: jaraco.context==6.0.1
Requires-Dist: jaraco.functools==4.1.0
Requires-Dist: Jinja2==3.1.6
Requires-Dist: keyring==25.6.0
Requires-Dist: markdown-it-py==3.0.0
Requires-Dist: MarkupSafe==3.0.2
Requires-Dist: mdurl==0.1.2
Requires-Dist: more-itertools==10.7.0
Requires-Dist: nh3==0.2.21
Requires-Dist: packaging==25.0
Requires-Dist: pillow==10.3.0
Requires-Dist: pycodestyle==2.13.0
Requires-Dist: Pygments==2.19.1
Requires-Dist: pyperclip==1.9.0
Requires-Dist: RapidFuzz==3.13.0
Requires-Dist: readme_renderer==44.0
Requires-Dist: requests==2.31.0
Requires-Dist: requests-toolbelt==1.0.0
Requires-Dist: rfc3986==2.0.0
Requires-Dist: rich==14.0.0
Requires-Dist: thefuzz==0.22.1
Requires-Dist: tkinterdnd2==0.3.0
Requires-Dist: tomli==2.2.1
Requires-Dist: twine==6.1.0
Requires-Dist: typing_extensions==4.13.2
Requires-Dist: urllib3==2.4.0
Requires-Dist: userpaths==0.1.3
Requires-Dist: zipp==3.22.0
Dynamic: author
Dynamic: author-email
Dynamic: classifier
Dynamic: description
Dynamic: description-content-type
Dynamic: home-page
Dynamic: project-url
Dynamic: requires-dist
Dynamic: requires-python
Dynamic: summary
